ShynaTelegramBotNotification/BotNotify.py
ShynaTelegramBotNotification/Notify_Boss.py
ShynaTelegramBotNotification/__init__.py
ShynaTelegramBotNotification-0.0.4.dist-info/LICENSE
ShynaTelegramBotNotification-0.0.4.dist-info/METADATA
ShynaTelegramBotNotification-0.0.4.dist-info/WHEEL
ShynaTelegramBotNotification-0.0.4.dist-info/top_level.txt
ShynaTelegramBotNotification-0.0.4.dist-info/RECORD
