Metadata-Version: 2.1
Name: ShynaTelegramBotNotification
Version: 0.0.4
Summary: Shyna Telegram Bot Notification.Notifications will be taken care by this package.
Author: Shivam Sharma
Author-email: shivamsharma1913@gmail.com
License-File: LICENSE
Requires-Dist: setuptools
Requires-Dist: wheel
Requires-Dist: ShynaTime
Requires-Dist: ShynaDatabase
Requires-Dist: python-telegram-bot
Requires-Dist: wget
